houhou/__init__.py
houhou/logger.py
houhou/logger_manager.py
houhou/sql_handler.py
houhou-1.0.1.dist-info/METADATA
houhou-1.0.1.dist-info/WHEEL
houhou-1.0.1.dist-info/top_level.txt
houhou-1.0.1.dist-info/RECORD
