Metadata-Version: 2.1
Name: houhou
Version: 1.0.1
Summary: This is for my own use
Author: hhh
Author-email: 
Classifier: Programming Language :: Python :: 3
Classifier: License :: OSI Approved :: Apache Software License
Classifier: Operating System :: OS Independent
